{"dataset": "nerel-bio", "name": "ACTIVITY", "description": "ACTIVITY - это сущности, такие как курение, алкоголь, курить, активность, обращение."}
{"dataset": "nerel-bio", "name": "ADMINISTRATION_ROUTE", "description": "ADMINISTRATION_ROUTE - это сущности, такие как внутривенно, инъекция, доступ, интравитреальный, капельный."}
{"dataset": "nerel-bio", "name": "AGE", "description": "AGE - это сущности, такие как год, старший, 60, 18, мес."}
{"dataset": "nerel-bio", "name": "ANATOMY", "description": "ANATOMY - это сущности, такие как артерия, мозг, кровь, головной, клетка."}
{"dataset": "nerel-bio", "name": "CHEM", "description": "CHEM - это сущности, такие как белок, раствор, препарат, кислота, рецептор."}
{"dataset": "nerel-bio", "name": "CITY", "description": "CITY - это сущности, такие как москва, новосибирск, город, монреальский, сибирский."}
{"dataset": "nerel-bio", "name": "COUNTRY", "description": "COUNTRY - это сущности, такие как российский, россия, китай, сша, республика."}
{"dataset": "nerel-bio", "name": "DATE", "description": "DATE - это сущности, такие как год, мес, день, течение, г."}
{"dataset": "nerel-bio", "name": "DEVICE", "description": "DEVICE - это сущности, такие как протез, иол, линза, шунт, компьютерный."}
{"dataset": "nerel-bio", "name": "DISO", "description": "DISO - это сущности, такие как опухоль, осложнение, нарушение, болезнь, заболевание."}
{"dataset": "nerel-bio", "name": "FACILITY", "description": "FACILITY - это сущности, такие как стационар, отделение, больница, клиника, городской."}
{"dataset": "nerel-bio", "name": "FINDING", "description": "FINDING - это сущности, такие как снижение, высокий, уровень, эффективность, эффект."}
{"dataset": "nerel-bio", "name": "FOOD", "description": "FOOD - это сущности, такие как алкоголь, алкогольный, пищевой, напиток, агд."}
{"dataset": "nerel-bio", "name": "GENE", "description": "GENE - это сущности, такие как ген, генотип, полиморфный, хромосома, маркер."}
{"dataset": "nerel-bio", "name": "HEALTH_CARE_ACTIVITY", "description": "HEALTH_CARE_ACTIVITY - это сущности, такие как диспансеризация,мощь, госпитализация, госпитализировать, медицинский."}
{"dataset": "nerel-bio", "name": "INJURY_POISONING", "description": "INJURY_POISONING - это сущности, такие как травма, ранение, повреждение, кровопотеря, чмт."}
{"dataset": "nerel-bio", "name": "LABPROC", "description": "LABPROC - это сущности, такие как исследование, томография, метод, мрт, анализ."}
{"dataset": "nerel-bio", "name": "LIVB", "description": "LIVB - это сущности, такие как группа, вирус, вич, животное, крыса."}
{"dataset": "nerel-bio", "name": "LOCATION", "description": "LOCATION - это сущности, такие как район, тихий, азия, африка, сибирь."}
{"dataset": "nerel-bio", "name": "MEDPROC", "description": "MEDPROC - это сущности, такие как терапия, операция, лечение, хирургический, резекция."}
{"dataset": "nerel-bio", "name": "MENTALPROC", "description": "MENTALPROC - это сущности, такие как когнитивный, психический, функция, эмоциональный, статус."}
{"dataset": "nerel-bio", "name": "NUMBER", "description": "NUMBER - это сущности, такие как 2, 1, 0,05, 3, 4."}
{"dataset": "nerel-bio", "name": "ORDINAL", "description": "ORDINAL - это сущности, такие как 2-й, 1-й, первый, 3-й, ii."}
{"dataset": "nerel-bio", "name": "ORGANIZATION", "description": "ORGANIZATION - это сущности, такие как больница, центр, ., отделение, здравоохранение."}
{"dataset": "nerel-bio", "name": "PERCENT", "description": "PERCENT - это сущности, такие как %, 95, 80, 100, 50."}
{"dataset": "nerel-bio", "name": "PERSON", "description": "PERSON - это сущности, такие как группа, пациент, больной, ребёнок, женщина."}
{"dataset": "nerel-bio", "name": "PHYS", "description": "PHYS - это сущности, такие как уровень, возраст, смертность, жизнь, кровоток."}
{"dataset": "nerel-bio", "name": "PRODUCT", "description": "PRODUCT - это сущности, такие как statistica, сигарета, 10, lentis, ls-312."}
{"dataset": "nerel-bio", "name": "PROFESSION", "description": "PROFESSION - это сущности, такие как врач, хирург, эксперт, медицинский, терапевт."}
{"dataset": "nerel-bio", "name": "SCIPROC", "description": "SCIPROC - это сущности, такие как шкала, исследование, анализ, оценка, р."}
{"dataset": "nerel-bio", "name": "STATE_OR_PROVINCE", "description": "STATE_OR_PROVINCE - это сущности, такие как область, республика, край, ставропольский, якутия."}
{"dataset": "nerel-bio", "name": "TIME", "description": "TIME - это сущности, такие как мина, ч, сутки, 12, день."}